pytexresume/__init__.py
pytexresume/cli.py
pytexresume/doc.py
pytexresume/infos.py
pytexresume/resume.py
pytexresume/templates/__init__.py
pytexresume/templates/en_simple/__init__.py
pytexresume/templates/en_simple/headers.yaml
pytexresume/templates/en_simple/resume.py
pytexresume-0.2.0.dist-info/METADATA
pytexresume-0.2.0.dist-info/WHEEL
pytexresume-0.2.0.dist-info/entry_points.txt
pytexresume-0.2.0.dist-info/RECORD
