Metadata-Version: 2.1
Name: pytexresume
Version: 0.2.0
Summary: A Python-based resume generator with LaTeX support.
License: MIT
Author: Your Name
Author-email: your.email@example.com
Requires-Python: >=3.10,<4.0
Classifier: License :: OSI Approved :: MIT License
Classifier: Programming Language :: Python :: 3
Classifier: Programming Language :: Python :: 3.10
Classifier: Programming Language :: Python :: 3.11
Classifier: Programming Language :: Python :: 3.12
Requires-Dist: PyYaml
Requires-Dist: gitpython
Requires-Dist: pydantic
Requires-Dist: pylatex
